sigllm/__init__.py
sigllm/benchmark.py
sigllm/core.py
sigllm/data.py
sigllm/pipelines/detector/gpt_detector.json
sigllm/pipelines/detector/mistral_detector.json
sigllm/pipelines/prompter/gpt_prompter.json
sigllm/pipelines/prompter/mistral_prompter.json
sigllm/pipelines/prompter/mistral_prompter_0shot.json
sigllm/pipelines/prompter/mistral_prompter_1shot.json
sigllm/pipelines/prompter/mistral_prompter_multivariate.json
sigllm/pipelines/prompter/mistral_prompter_multivariate_0shot.json
sigllm/pipelines/prompter/prompter_artificialwithanomaly.json
sigllm/pipelines/prompter/prompter_realadexchange.json
sigllm/pipelines/prompter/prompter_realawscloudwatch.json
sigllm/pipelines/prompter/prompter_realtraffic.json
sigllm/pipelines/prompter/prompter_realtweets.json
sigllm/pipelines/prompter/prompter_smap.json
sigllm/primitives/__init__.py
sigllm/primitives/postprocessing.py
sigllm/primitives/transformation.py
sigllm/primitives/forecasting/TEMPLATE.json
sigllm/primitives/forecasting/__init__.py
sigllm/primitives/forecasting/gpt.py
sigllm/primitives/forecasting/huggingface.py
sigllm/primitives/jsons/sigllm.primitives.forecasting.gpt.GPT.json
sigllm/primitives/jsons/sigllm.primitives.forecasting.huggingface.HF.json
sigllm/primitives/jsons/sigllm.primitives.postprocessing.aggregate_rolling_window.json
sigllm/primitives/jsons/sigllm.primitives.prompting.anomalies.find_anomalies_in_windows.json
sigllm/primitives/jsons/sigllm.primitives.prompting.anomalies.format_anomalies.json
sigllm/primitives/jsons/sigllm.primitives.prompting.anomalies.merge_anomalous_sequences.json
sigllm/primitives/jsons/sigllm.primitives.prompting.anomalies.parse_anomaly_response.json
sigllm/primitives/jsons/sigllm.primitives.prompting.anomalies.val2idx.json
sigllm/primitives/jsons/sigllm.primitives.prompting.gpt.GPT.json
sigllm/primitives/jsons/sigllm.primitives.prompting.huggingface.HF.json
sigllm/primitives/jsons/sigllm.primitives.prompting.timeseries_preprocessing.rolling_window_sequences.json
sigllm-0.1.0.dist-info/licenses/LICENSE
sigllm-0.1.0.dist-info/METADATA
sigllm-0.1.0.dist-info/WHEEL
sigllm-0.1.0.dist-info/entry_points.txt
sigllm-0.1.0.dist-info/top_level.txt
sigllm-0.1.0.dist-info/RECORD
