Metadata-Version: 2.4
Name: sigllm
Version: 0.1.0
Summary: LLMs for unsupervised time series anomaly detection
Author-email: MIT Data To AI Lab <dailabmit@gmail.com>
License: MIT license
Project-URL: homepage, https://github.com/sintel-dev/sigllm/
Keywords: sigllm,LLM4TS,timeseries,anomaly-detection
Classifier: Development Status :: 2 - Pre-Alpha
Classifier: Intended Audience :: Developers
Classifier: License :: OSI Approved :: MIT License
Classifier: Natural Language :: English
Classifier: Programming Language :: Python :: 3
Classifier: Programming Language :: Python :: 3.9
Classifier: Programming Language :: Python :: 3.10
Classifier: Programming Language :: Python :: 3.11
Requires-Python: <3.12,>=3.9
License-File: LICENSE
Requires-Dist: numpy<2,>=1.17.5
Requires-Dist: pandas<2,>=1.0.0
Requires-Dist: scikit-learn<2,>=0.22.1
Requires-Dist: orion-ml<0.8,>=0.6
Requires-Dist: ml-stars<0.4,>=0.2.1
Requires-Dist: openai>=1.46.0
Requires-Dist: tiktoken>=0.7.0
Requires-Dist: transformers>=4.44.2
Requires-Dist: torch>=1.4.0
Requires-Dist: accelerate>=0.34.2
Requires-Dist: sentencepiece>=0.2.0
Provides-Extra: test
Requires-Dist: pytest>=3.4.2; extra == "test"
Requires-Dist: pytest-cov>=2.6.0; extra == "test"
Requires-Dist: pytest-runner>=2.11.1; extra == "test"
Requires-Dist: rundoc<0.5,>=0.4.3; extra == "test"
Requires-Dist: tomli<3,>=2.0.0; extra == "test"
Provides-Extra: dev
Requires-Dist: sigllm[test]; extra == "dev"
Requires-Dist: build<2,>=1.0.0; extra == "dev"
Requires-Dist: bump-my-version>=0.18.3; extra == "dev"
Requires-Dist: pip>=9.0.1; extra == "dev"
Requires-Dist: watchdog>=0.8.3; extra == "dev"
Requires-Dist: docutils<0.18,>=0.12; extra == "dev"
Requires-Dist: m2r2<0.3,>=0.2.5; extra == "dev"
Requires-Dist: nbsphinx<0.7,>=0.5.0; extra == "dev"
Requires-Dist: Sphinx<3.3,>=3; extra == "dev"
Requires-Dist: pydata-sphinx-theme<0.5; extra == "dev"
Requires-Dist: markupsafe<2.1.0; extra == "dev"
Requires-Dist: ipython<9,>=6.5; extra == "dev"
Requires-Dist: alabaster<=0.7.12; extra == "dev"
Requires-Dist: sphinxcontrib-applehelp<1.0.8; extra == "dev"
Requires-Dist: sphinxcontrib-devhelp<1.0.6; extra == "dev"
Requires-Dist: sphinxcontrib-htmlhelp<2.0.5; extra == "dev"
Requires-Dist: sphinxcontrib-serializinghtml<1.1.10; extra == "dev"
Requires-Dist: sphinxcontrib-qthelp<1.0.7; extra == "dev"
Requires-Dist: Jinja2<3,>=2; extra == "dev"
Requires-Dist: ruff>=0.4.5; extra == "dev"
Requires-Dist: twine>=1.10.0; extra == "dev"
Requires-Dist: wheel>=0.30.0; extra == "dev"
Requires-Dist: coverage>=4.5.1; extra == "dev"
Requires-Dist: tox>=2.9.1; extra == "dev"
Requires-Dist: invoke; extra == "dev"
Dynamic: license-file
